trainer/VERSION
trainer/__init__.py
trainer/analytics.py
trainer/callbacks.py
trainer/distribute.py
trainer/generic_utils.py
trainer/io.py
trainer/logger.py
trainer/model.py
trainer/torch.py
trainer/trainer.py
trainer/trainer_utils.py
trainer/logging/__init__.py
trainer/logging/aim_logger.py
trainer/logging/base_dash_logger.py
trainer/logging/clearml_logger.py
trainer/logging/console_logger.py
trainer/logging/dummy_logger.py
trainer/logging/mlflow_logger.py
trainer/logging/tensorboard_logger.py
trainer/logging/wandb_logger.py
trainer/utils/__init__.py
trainer/utils/cpu_memory.py
trainer/utils/cuda_memory.py
trainer/utils/distributed.py
trainer-0.0.36.dist-info/METADATA
trainer-0.0.36.dist-info/WHEEL
trainer-0.0.36.dist-info/top_level.txt
trainer-0.0.36.dist-info/RECORD
