Metadata-Version: 2.1
Name: trainer
Version: 0.0.36
Summary: General purpose model trainer for PyTorch that is more flexible than it should be, by 🐸Coqui.
Home-page: https://github.com/coqui-ai/Trainer
Author: Eren Gölge
Author-email: egolge@coqui.ai
License: Apache2
Project-URL: Documentation, https://github.com/coqui-ai/Trainer/
Project-URL: Tracker, https://github.com/coqui-ai/Trainer/issues
Project-URL: Repository, https://github.com/coqui-ai/Trainer
Project-URL: Discussions, https://github.com/coqui-ai/Trainer/discussions
Classifier: Environment :: Console
Classifier: Natural Language :: English
Classifier: Development Status :: 3 - Alpha
Classifier: Intended Audience :: Developers
Classifier: License :: OSI Approved :: Apache Software License
Classifier: Operating System :: OS Independent
Classifier: Programming Language :: Python :: 3.8
Classifier: Programming Language :: Python :: 3.9
Classifier: Programming Language :: Python :: 3.10
Classifier: Programming Language :: Python :: 3.11
Requires-Python: >=3.6.0, <3.12
Requires-Dist: torch>=1.7
Requires-Dist: coqpit
Requires-Dist: psutil
Requires-Dist: fsspec
Requires-Dist: tensorboard
Requires-Dist: soundfile
Provides-Extra: dev
Requires-Dist: black; extra == "dev"
Requires-Dist: coverage; extra == "dev"
Requires-Dist: isort; extra == "dev"
Requires-Dist: pytest; extra == "dev"
Requires-Dist: pylint; extra == "dev"
Requires-Dist: accelerate; extra == "dev"
Provides-Extra: test
Requires-Dist: torchvision; extra == "test"
Provides-Extra: all
Requires-Dist: torch>=1.7; extra == "all"
Requires-Dist: coqpit; extra == "all"
Requires-Dist: psutil; extra == "all"
Requires-Dist: fsspec; extra == "all"
Requires-Dist: tensorboard; extra == "all"
Requires-Dist: soundfile; extra == "all"
Requires-Dist: black; extra == "all"
Requires-Dist: coverage; extra == "all"
Requires-Dist: isort; extra == "all"
Requires-Dist: pytest; extra == "all"
Requires-Dist: pylint; extra == "all"
Requires-Dist: accelerate; extra == "all"
Requires-Dist: torchvision; extra == "all"
